Metadata-Version: 2.1
Name: CodeExecutor
Version: 1.1
Summary: Running code in a sandbox environment
Home-page: UNKNOWN
Author-email: neuralteam@mail.ru
License: UNKNOWN
Platform: UNKNOWN
